kintu/__init__.py
kintu/main.py
kintu-0.0.1.dist-info/licenses/LICENSE
kintu-0.0.1.dist-info/WHEEL
kintu-0.0.1.dist-info/METADATA
kintu-0.0.1.dist-info/RECORD
