Metadata-Version: 2.4
Name: kintu
Version: 0.0.1
Summary: Generic multi-provider LLM library
Author-email: Your Name <your.email@example.com>
Requires-Python: >=3.10
Classifier: Development Status :: 3 - Alpha
Classifier: Intended Audience :: Developers
Classifier: License :: OSI Approved :: MIT License
Classifier: Programming Language :: Python :: 3
Classifier: Programming Language :: Python :: 3.10
Classifier: Programming Language :: Python :: 3.11
Classifier: Programming Language :: Python :: 3.12
Classifier: Programming Language :: Python :: 3.13
License-File: LICENSE
Project-URL: Homepage, https://github.com/armandmcqueen/kintu
Project-URL: Issues, https://github.com/armandmcqueen/kintu/issues
Project-URL: Repository, https://github.com/armandmcqueen/kintu.git
